textprivacy/__init__.py
textprivacy/cli.py
textprivacy/textanonymization.py
textprivacy/textpseudonymization.py
textprivacy/utils.py
DaAnonymization-0.1.1.dist-info/AUTHORS.rst
DaAnonymization-0.1.1.dist-info/LICENSE
DaAnonymization-0.1.1.dist-info/METADATA
DaAnonymization-0.1.1.dist-info/WHEEL
DaAnonymization-0.1.1.dist-info/entry_points.txt
DaAnonymization-0.1.1.dist-info/top_level.txt
DaAnonymization-0.1.1.dist-info/RECORD
