Metadata-Version: 2.1
Name: DaAnonymization
Version: 0.1.1
Summary: A simple pipeline wrapped around SpaCy and DaCy for anonymizing danish corpora.
Home-page: https://github.com/martincjespersen/DaAnonymization
Author: Martin Closter Jespersen
Author-email: martincjespersen@gmail.com
License: Apache license Version 2.0
Keywords: DaAnonymization
Platform: UNKNOWN
Classifier: Development Status :: 2 - Pre-Alpha
Classifier: Intended Audience :: Developers
Classifier: License :: OSI Approved :: Apache Software License
Classifier: Natural Language :: English
Classifier: Programming Language :: Python :: 3
Classifier: Programming Language :: Python :: 3.6
Classifier: Programming Language :: Python :: 3.7
Classifier: Programming Language :: Python :: 3.8
Classifier: Programming Language :: Python :: 3.9
Requires-Python: >=3.6
Requires-Dist: dacy
